gobrec/__init__.py
gobrec/recommender.py
gobrec/mabs/__init__.py
gobrec/mabs/mab_algo.py
gobrec/mabs/random_mab.py
gobrec/mabs/lin_mabs/__init__.py
gobrec/mabs/lin_mabs/lin.py
gobrec/mabs/lin_mabs/lin_greedy.py
gobrec/mabs/lin_mabs/lin_ts.py
gobrec/mabs/lin_mabs/lin_ucb.py
gobrec-1.0.6.dist-info/licenses/LICENSE
gobrec-1.0.6.dist-info/METADATA
gobrec-1.0.6.dist-info/WHEEL
gobrec-1.0.6.dist-info/top_level.txt
gobrec-1.0.6.dist-info/RECORD
