Metadata-Version: 2.4
Name: gobrec
Version: 1.0.6
Summary: GOBRec: GPU Optimized Bandits Recommender
Author-email: Gregório Fornetti Azevedo <gregorio.fornetti@estudante.ufscar.br>, Pedro Rei Pires <pedro.pires@dcomp.sor.ufscar.br>, Rafael Tofoli Sereicikas <rafaeltofoli@estudante.ufscar.br>, Tiago Agostinho de Almeida <talmeida@ufscar.br>
License-Expression: MIT
Project-URL: Documentation, https://ufscar-lasid.github.io/gobrec/
Project-URL: Repository, https://github.com/UFSCar-LaSID/gobrec
Keywords: recommender-systems,bandits,contextual-bandits,gpu,pytorch
Classifier: Development Status :: 4 - Beta
Classifier: Intended Audience :: Science/Research
Classifier: Topic :: Scientific/Engineering :: Artificial Intelligence
Classifier: Programming Language :: Python :: 3
License-File: LICENSE
Requires-Dist: torch
Requires-Dist: numpy
Dynamic: license-file
